Metadata-Version: 2.1
Name: odoo-addon-github_connector
Version: 18.0.1.0.0.2
Requires-Python: >=3.10
Requires-Dist: GitPython
Requires-Dist: PyGithub
Requires-Dist: odoo==18.0.*
Requires-Dist: pathspec
Summary: Synchronize information from Github repositories
Home-page: https://github.com/OCA/interface-github
License: AGPL-3
Author: Odoo Community Association (OCA), GRAP, Akretion, Tecnativa
Author-email: support@odoo-community.org
Classifier: Programming Language :: Python
Classifier: Framework :: Odoo
Classifier: Framework :: Odoo :: 18.0
Classifier: License :: OSI Approved :: GNU Affero General Public License v3
